stactools/cgls_lc100/__init__.py
stactools/cgls_lc100/cog.py
stactools/cgls_lc100/commands.py
stactools/cgls_lc100/constants.py
stactools/cgls_lc100/stac.py
stactools/cgls_lc100/version.py
stactools_cgls_lc100-0.1.6.dist-info/METADATA
stactools_cgls_lc100-0.1.6.dist-info/WHEEL
stactools_cgls_lc100-0.1.6.dist-info/top_level.txt
stactools_cgls_lc100-0.1.6.dist-info/RECORD
